ot4_lib/__init__.py
ot4_lib/cacheops.py
ot4_lib/celery.py
ot4_lib/env.py
ot4_lib/models.py
ot4_lib/shortuuidx.py
ot4_lib/ot4manager/__init__.py
ot4_lib/ot4manager/apps.py
ot4_lib/ot4manager/models.py
ot4_lib/ot4manager/management/__init__.py
ot4_lib/ot4manager/management/commands/__init__.py
ot4_lib/ot4manager/management/commands/_common.py
ot4_lib/ot4manager/management/commands/webdump.py
ot4_lib/ot4manager/management/commands/webload.py
ot4_lib-24.12.7.dist-info/METADATA
ot4_lib-24.12.7.dist-info/WHEEL
ot4_lib-24.12.7.dist-info/licenses/LICENSE
ot4_lib-24.12.7.dist-info/RECORD
