Metadata-Version: 2.4
Name: ot4-lib
Version: 24.12.7
Summary: Shared stuff for Outlaw projects
Author-email: yokotoka <hey@yokotoka.is>
License-File: LICENSE
Requires-Python: >=3.10
Requires-Dist: celery>=5.4.0
Requires-Dist: django
Requires-Dist: django-cacheops>=7.0.2
Requires-Dist: django-environ>=0.11.2
Requires-Dist: django-extensions>=3.2.3
Requires-Dist: loguru>=0.7.2
Requires-Dist: niquests>=3.11.2
Requires-Dist: shortuuid==1.0.13
